setup.py
sdk/__init__.py
sdk/accounts.py
sdk/base_resource.py
sdk/cookbooks.py
sdk/groups.py
sdk/iam.py
sdk/images.py
sdk/layer_blueprints.py
sdk/layers.py
sdk/leases.py
sdk/projects.py
sdk/recipes.py
sdk/repositories.py
sdk/restrictions.py
sdk/sdk.py
sdk/stack_blueprints.py
sdk/stacks.py
sdk/tokens.py
sdk/users.py
test/test_cli.py
xms_sdk.egg-info/PKG-INFO
xms_sdk.egg-info/SOURCES.txt
xms_sdk.egg-info/dependency_links.txt
xms_sdk.egg-info/requires.txt
xms_sdk.egg-info/top_level.txt