Metadata-Version: 1.0
Name: xms-sdk
Version: 1.0
Summary: The SDK used to interact with XMS.
Home-page: UNKNOWN
Author: UNKNOWN
Author-email: UNKNOWN
License: UNKNOWN
Platform: UNKNOWN
